papyrus/__init__.py
papyrus/query.py
papyrus/analysis/__init__.py
papyrus/analysis/analysis.py
papyrus/data/__init__.py
papyrus/data/reader.py
papyrus/modeling/__init__.py
papyrus/modeling/modeling.py
papyrus/preprocessing/__init__.py
papyrus/preprocessing/preprocessing.py
papyrus/preprocessing/preprocessing_inference.py
papyrus/supplementaries/__init__.py
papyrus/supplementaries/handlers.py
papyrus/supplementaries/main.py
papyrus_ai-0.0.5.dist-info/LICENSE
papyrus_ai-0.0.5.dist-info/METADATA
papyrus_ai-0.0.5.dist-info/WHEEL
papyrus_ai-0.0.5.dist-info/top_level.txt
papyrus_ai-0.0.5.dist-info/RECORD
