Metadata-Version: 2.1
Name: papyrus-ai
Version: 0.0.5
Summary: High-level grammar interface for ML
Home-page: https://github.com/Palashio/papyrus
Author: Palash Shah
Author-email: hello@paraglide.ai
License: UNKNOWN
Platform: UNKNOWN
Classifier: Programming Language :: Python :: 3
Classifier: License :: OSI Approved :: MIT License
Classifier: Operating System :: OS Independent
Requires-Python: >=3.6
License-File: LICENSE
Requires-Dist: sklearn
Requires-Dist: numpy
Requires-Dist: pandas
Requires-Dist: xgboost
Requires-Dist: setuptools
Requires-Dist: nltk
Requires-Dist: bentoml
Requires-Dist: autocorrect
Requires-Dist: prince
